edusoho/__init__.py
edusoho/__main__.py
edusoho/server.py
mcp_server_edusoho-0.1.0.dist-info/METADATA
mcp_server_edusoho-0.1.0.dist-info/WHEEL
mcp_server_edusoho-0.1.0.dist-info/entry_points.txt
mcp_server_edusoho-0.1.0.dist-info/top_level.txt
mcp_server_edusoho-0.1.0.dist-info/RECORD
