Metadata-Version: 2.4
Name: mcp-server-edusoho
Version: 0.1.0
Summary: edusoho mcp server
Requires-Python: >=3.12
Requires-Dist: httpx>=0.28.1
Requires-Dist: mcp[cli]>=1.2.0
